{
    "apiUrl":"http://localhost:8002/api/",

    "apiKey":"special-key",

    "defaultServiceBaseClass":"SwaggerApi",

    "defaultModelBaseClass":"Object",

    "serviceBaseClasses":{},

    "defaultModelImports":[],

    "defaultServiceImports":[],

    "modelPackageName":"com.wordnik.swagger.model",

    "apiPackageName":"com.wordnik.swagger.api",

    "ignoreMethods":[],

    "ignoreModels":[],

    "outputDirectory":"../swagger-sample-app/sdk-libs/src/main/as3/com/wordnik/swagger/",

    "libraryHome":"../swagger-sample-app/sdk-libs"
}