{
  "docs": {
    "Getting Started": [
      "installation",
      "plugins",
      "online",
      "usage"
    ],
    "Extending": [
      "templating",
      "customization",
      "integrations"
    ],
    "Contributing": [
      "contributing",
      "code-of-conduct",
      "contribute-building"
    ],
    "About": [
      "roadmap",
      "faq",
      "swagger-codegen-migration",
      "fork-qna"
    ],

    "Releases": [
      "release-3-0-0"
    ],

    "API": [
      "generators"
    ]
  },
  "docs-other": {
    "First Category": ["doc4", "doc5"]
  }
}
